selench/__init__.py
selench/driver.py
selench/element.py
selench/expect.py
selench-2024.5.2.dist-info/LICENSE
selench-2024.5.2.dist-info/METADATA
selench-2024.5.2.dist-info/WHEEL
selench-2024.5.2.dist-info/top_level.txt
selench-2024.5.2.dist-info/RECORD
