Metadata-Version: 2.1
Name: selench
Version: 2024.5.2
Summary: Selenium wrapper for Python
Home-page: https://github.com/dsymbol/selench
Author: dsymbol
License: OSI Approved :: MIT License
Classifier: Programming Language :: Python :: 3
Classifier: License :: OSI Approved :: MIT License
License-File: LICENSE
Requires-Dist: selenium ==4.19.0
Requires-Dist: pytest
